geoffrey_csslint-0.0.1.dist-info/DESCRIPTION.rst
geoffrey_csslint-0.0.1.dist-info/RECORD
geoffrey_csslint-0.0.1.dist-info/WHEEL
geoffrey_csslint-0.0.1.dist-info/top_level.txt
geoffrey_csslint-0.0.1.dist-info/metadata.json
geoffrey_csslint-0.0.1.dist-info/METADATA
geoffreyplugins/__init__.py
geoffreyplugins/csslint.py
geoffreyplugins/csslint/main.js
geoffreyplugins/csslint/assets/.gitkeep
