Metadata-Version: 2.0
Name: geoffrey-csslint
Version: 0.0.1
Summary: CSSLint is a tool to help point out problems with your CSS code.
Home-page: https://github.com/GeoffreyCI/geoffrey-csslint
Author: Miguel Reguero Bejar
Author-email: mreguerob0@gmail.com
License: UNKNOWN
Platform: UNKNOWN
